demuxEM/__init__.py
demuxEM/__main__.py
demuxEM/version.py
demuxEM/commands/Base.py
demuxEM/commands/DemuxEM.py
demuxEM/commands/__init__.py
demuxEM/pipeline/__init__.py
demuxEM/pipeline/pipeline.py
demuxEM/tools/__init__.py
demuxEM/tools/demuxEM.py
demuxEM/tools/down_sampling.py
demuxEM/tools/plot.py
demuxem-0.1.8.dist-info/licenses/LICENSE
demuxem-0.1.8.dist-info/METADATA
demuxem-0.1.8.dist-info/WHEEL
demuxem-0.1.8.dist-info/entry_points.txt
demuxem-0.1.8.dist-info/top_level.txt
demuxem-0.1.8.dist-info/RECORD
